demo_reader/__init__.py
demo_reader/__main__.py
demo_reader/multireader.py
demo_reader/util/__init__.py
demo_reader/util/writer.py
demo_reader_eb-1.0.0.dist-info/METADATA
demo_reader_eb-1.0.0.dist-info/WHEEL
demo_reader_eb-1.0.0.dist-info/top_level.txt
demo_reader_eb-1.0.0.dist-info/RECORD
